encx-0.2.data/scripts/encx
encx-0.2.dist-info/DESCRIPTION.rst
encx-0.2.dist-info/METADATA
encx-0.2.dist-info/RECORD
encx-0.2.dist-info/WHEEL
encx-0.2.dist-info/metadata.json
encx-0.2.dist-info/top_level.txt
encxlib/__init__.py
encxlib/cli.py
encxlib/commands.py
encxlib/schemes.py
encxlib/security.py
encxlib/spec.py
encxlib/tests.py
