Metadata-Version: 2.0
Name: encx
Version: 0.2
Summary: Encryption CLI tool and implementation of the encx file format.
Home-page: https://github.com/jdotpy/encx
Author: KJ
Author-email: jdotpy@users.noreply.github.com
License: UNKNOWN
Platform: UNKNOWN
Requires-Dist: cryptography
Requires-Dist: pyyaml
